LICENSE
MANIFEST.in
README.md
requirements.txt
setup.py
easy_celery/__init__.py
easy_celery/__version__.py
easy_celery/core.py
easy_celery.egg-info/PKG-INFO
easy_celery.egg-info/SOURCES.txt
easy_celery.egg-info/dependency_links.txt
easy_celery.egg-info/requires.txt
easy_celery.egg-info/top_level.txt